setup.py
falcon_wing.egg-info/PKG-INFO
falcon_wing.egg-info/SOURCES.txt
falcon_wing.egg-info/dependency_links.txt
falcon_wing.egg-info/requires.txt
falcon_wing.egg-info/top_level.txt
wing/__init__.py
wing/api.py
wing/cache.py
wing/errors.py
wing/fields.py
wing/resources.py
wing/settings.py
wing/adapters/__init__.py
wing/adapters/peewee.py
wing/falcon/__init__.py
wing/falcon/errors.py
wing/falcon/middlewares.py
wing/falcon/resources.py
wing/serialization/__init__.py
wing/serialization/json.py
wing/serialization/yaml.py