Metadata-Version: 1.0
Name: falcon-wing
Version: 0.3.1
Summary: Falcon extension for building nice looking API
Home-page: UNKNOWN
Author: Vlad Bakin
Author-email: UNKNOWN
License: UNKNOWN
Platform: UNKNOWN
